Workbook

Sheet Auto Menu
A1: CTC COMMISSARY MENU
A3: CLOTHING, SHOES, & UNDERWEAR
A4: THERMAL TOPS | F4: THERMAL BOTTOMS | K4: THERMAL SETS
B5: 1021 | C5: =INDEX('Master List Import'!$A$2:$P$700, MATCH('Auto Menu'!$B5, 'Master List Import'!$M$2:$M$700), 14) -> Thermal Top (Sm) | D5: =INDEX('Master List Import'!$A$2:$P$700, MATCH('Auto Menu'!$B5, 'Master List Import'!$M$2:$M$700), 16) -> 8.7 | G5: 1041 | H5: =INDEX('Master List Import'!$A$2:$P$700, MATCH('Auto Menu'!$G5, 'Master List Import'!$M$2:$M$700), 14) -> Thermal Bottom (Sm) | I5: =INDEX('Master List Import'!$A$2:$P$700, MATCH('Auto Menu'!$G5, 'Master List Import'!$M$2:$M$700), 16) -> 8.7 | L5: 1001 | M5: =INDEX('Master List Import'!$A$2:$P$700, MATCH('Auto Menu'!$L5, 'Master List Import'!$M$2:$M$700), 14) -> Thermal Set (Sm) | N5: =INDEX('Master List Import'!$A$2:$P$700, MATCH('Auto Menu'!$L5, 'Master List Import'!$M$2:$M$700), 16) -> 17.4
B6: 1022 | C6: =INDEX('Master List Import'!$A$2:$P$700, MATCH('Auto Menu'!$B6, 'Master List Import'!$M$2:$M$700), 14) -> Thermal Top (Md) | D6: =INDEX('Master List Import'!$A$2:$P$700, MATCH('Auto Menu'!$B6, 'Master List Import'!$M$2:$M$700), 16) -> 8.7 | G6: 1042 | H6: =INDEX('Master List Import'!$A$2:$P$700, MATCH('Auto Menu'!$G6, 'Master List Import'!$M$2:$M$700), 14) -> Thermal Bottom (Md) | I6: =INDEX('Master List Import'!$A$2:$P$700, MATCH('Auto Menu'!$G6, 'Master List Import'!$M$2:$M$700), 16) -> 8.7 | L6: 1002 | M6: =INDEX('Master List Import'!$A$2:$P$700, MATCH('Auto Menu'!$L6, 'Master List Import'!$M$2:$M$700), 14) -> Thermal Set (Md) | N6: =INDEX('Master List Import'!$A$2:$P$700, MATCH('Auto Menu'!$L6, 'Master List Import'!$M$2:$M$700), 16) -> 17.4
B7: 1023 | C7: =INDEX('Master List Import'!$A$2:$P$700, MATCH('Auto Menu'!$B7, 'Master List Import'!$M$2:$M$700), 14) -> Thermal Top (Lg) | D7: =INDEX('Master List Import'!$A$2:$P$700, MATCH('Auto Menu'!$B7, 'Master List Import'!$M$2:$M$700), 16) -> 8.7 | G7: 1043 | H7: =INDEX('Master List Import'!$A$2:$P$700, MATCH('Auto Menu'!$G7, 'Master List Import'!$M$2:$M$700), 14) -> Thermal Bottom (Lg) | I7: =INDEX('Master List Import'!$A$2:$P$700, MATCH('Auto Menu'!$G7, 'Master List Import'!$M$2:$M$700), 16) -> 8.7 | L7: 1003 | M7: =INDEX('Master List Import'!$A$2:$P$700, MATCH('Auto Menu'!$L7, 'Master List Import'!$M$2:$M$700), 14) -> Thermal Set (Lg) | N7: =INDEX('Master List Import'!$A$2:$P$700, MATCH('Auto Menu'!$L7, 'Master List Import'!$M$2:$M$700), 16) -> 17.4
B8: 1024 | C8: =INDEX('Master List Import'!$A$2:$P$700, MATCH('Auto Menu'!$B8, 'Master List Import'!$M$2:$M$700), 14) -> Thermal Top (XL) | D8: =INDEX('Master List Import'!$A$2:$P$700, MATCH('Auto Menu'!$B8, 'Master List Import'!$M$2:$M$700), 16) -> 8.7 | G8: 1044 | H8: =INDEX('Master List Import'!$A$2:$P$700, MATCH('Auto Menu'!$G8, 'Master List Import'!$M$2:$M$700), 14) -> Thermal Bottom (XL) | I8: =INDEX('Master List Import'!$A$2:$P$700, MATCH('Auto Menu'!$G8, 'Master List Import'!$M$2:$M$700), 16) -> 8.7 | L8: 1004 | M8: =INDEX('Master List Import'!$A$2:$P$700, MATCH('Auto Menu'!$L8, 'Master List Import'!$M$2:$M$700), 14) -> Thermal Set (XL) | N8: =INDEX('Master List Import'!$A$2:$P$700, MATCH('Auto Menu'!$L8, 'Master List Import'!$M$2:$M$700), 16) -> 17.4
B9: 1025 | C9: =INDEX('Master List Import'!$A$2:$P$700, MATCH('Auto Menu'!$B9, 'Master List Import'!$M$2:$M$700), 14) -> Thermal Top (2X) | D9: =INDEX('Master List Import'!$A$2:$P$700, MATCH('Auto Menu'!$B9, 'Master List Import'!$M$2:$M$700), 16) -> 10.2 | G9: 1045 | H9: =INDEX('Master List Import'!$A$2:$P$700, MATCH('Auto Menu'!$G9, 'Master List Import'!$M$2:$M$700), 14) -> Thermal Bottom (2X) | I9: =INDEX('Master List Import'!$A$2:$P$700, MATCH('Auto Menu'!$G9, 'Master List Import'!$M$2:$M$700), 16) -> 10.2 | L9: 1005 | M9: =INDEX('Master List Import'!$A$2:$P$700, MATCH('Auto Menu'!$L9, 'Master List Import'!$M$2:$M$700), 14) -> Thermal Set (2X) | N9: =INDEX('Master List Import'!$A$2:$P$700, MATCH('Auto Menu'!$L9, 'Master List Import'!$M$2:$M$700), 16) -> 20.4
B10: 1026 | C10: =INDEX('Master List Import'!$A$2:$P$700, MATCH('Auto Menu'!$B10, 'Master List Import'!$M$2:$M$700), 14) -> Thermal Top (3X) | D10: =INDEX('Master List Import'!$A$2:$P$700, MATCH('Auto Menu'!$B10, 'Master List Import'!$M$2:$M$700), 16) -> 10.9 | G10: 1046 | H10: =INDEX('Master List Import'!$A$2:$P$700, MATCH('Auto Menu'!$G10, 'Master List Import'!$M$2:$M$700), 14) -> Thermal Bottom (3X) | I10: =INDEX('Master List Import'!$A$2:$P$700, MATCH('Auto Menu'!$G10, 'Master List Import'!$M$2:$M$700), 16) -> 10.9 | L10: 1006 | M10: =INDEX('Master List Import'!$A$2:$P$700, MATCH('Auto Menu'!$L10, 'Master List Import'!$M$2:$M$700), 14) -> Thermal Set (3X) | N10: =INDEX('Master List Import'!$A$2:$P$700, MATCH('Auto Menu'!$L10, 'Master List Import'!$M$2:$M$700), 16) -> 21.8
B11: 1027 | C11: =INDEX('Master List Import'!$A$2:$P$700, MATCH('Auto Menu'!$B11, 'Master List Import'!$M$2:$M$700), 14) -> Thermal Top (4X) | D11: =INDEX('Master List Import'!$A$2:$P$700, MATCH('Auto Menu'!$B11, 'Master List Import'!$M$2:$M$700), 16) -> 11.6 | G11: 1047 | H11: =INDEX('Master List Import'!$A$2:$P$700, MATCH('Auto Menu'!$G11, 'Master List Import'!$M$2:$M$700), 14) -> Thermal Bottom (4X) | I11: =INDEX('Master List Import'!$A$2:$P$700, MATCH('Auto Menu'!$G11, 'Master List Import'!$M$2:$M$700), 16) -> 11.6 | L11: 1007 | M11: =INDEX('Master List Import'!$A$2:$P$700, MATCH('Auto Menu'!$L11, 'Master List Import'!$M$2:$M$700), 14) -> Thermal Set (4X) | N11: =INDEX('Master List Import'!$A$2:$P$700, MATCH('Auto Menu'!$L11, 'Master List Import'!$M$2:$M$700), 16) -> 23.2
B12: 1028 | C12: =INDEX('Master List Import'!$A$2:$P$700, MATCH('Auto Menu'!$B12, 'Master List Import'!$M$2:$M$700), 14) -> Thermal Top (5X) | D12: =INDEX('Master List Import'!$A$2:$P$700, MATCH('Auto Menu'!$B12, 'Master List Import'!$M$2:$M$700), 16) -> 12.6 | G12: 1048 | H12: =INDEX('Master List Import'!$A$2:$P$700, MATCH('Auto Menu'!$G12, 'Master List Import'!$M$2:$M$700), 14) -> Thermal Bottom (5X) | I12: =INDEX('Master List Import'!$A$2:$P$700, MATCH('Auto Menu'!$G12, 'Master List Import'!$M$2:$M$700), 16) -> 12.6 | L12: 1008 | M12: =INDEX('Master List Import'!$A$2:$P$700, MATCH('Auto Menu'!$L12, 'Master List Import'!$M$2:$M$700), 14) -> Thermal Set (5X) | N12: =INDEX('Master List Import'!$A$2:$P$700, MATCH('Auto Menu'!$L12, 'Master List Import'!$M$2:$M$700), 16) -> 25.2
A14: SWEATSHIRTS | F14: SWEATPANTS | K14: T-SHIRTS
B15: 1061 | C15: =INDEX('Master List Import'!$A$2:$P$700, MATCH('Auto Menu'!$B15, 'Master List Import'!$M$2:$M$700), 14) -> Grey Sweatshirt (Md) | D15: =INDEX('Master List Import'!$A$2:$P$700, MATCH('Auto Menu'!$B15, 'Master List Import'!$M$2:$M$700), 16) -> 21 | G15: 1071 | H15: =INDEX('Master List Import'!$A$2:$P$700, MATCH('Auto Menu'!$G15, 'Master List Import'!$M$2:$M$700), 14) -> Grey Sweatpants (Md) | I15: =INDEX('Master List Import'!$A$2:$P$700, MATCH('Auto Menu'!$G15, 'Master List Import'!$M$2:$M$700), 16) -> 25 | L15: 1201 | M15: =INDEX('Master List Import'!$A$2:$P$700, MATCH('Auto Menu'!$L15, 'Master List Import'!$M$2:$M$700), 14) -> White T-Shirt (Sm) | N15: =INDEX('Master List Import'!$A$2:$P$700, MATCH('Auto Menu'!$L15, 'Master List Import'!$M$2:$M$700), 16) -> 5.05
B16: 1062 | C16: =INDEX('Master List Import'!$A$2:$P$700, MATCH('Auto Menu'!$B16, 'Master List Import'!$M$2:$M$700), 14) -> Grey Sweatshirt (Lg) | D16: =INDEX('Master List Import'!$A$2:$P$700, MATCH('Auto Menu'!$B16, 'Master List Import'!$M$2:$M$700), 16) -> 21 | G16: 1072 | H16: =INDEX('Master List Import'!$A$2:$P$700, MATCH('Auto Menu'!$G16, 'Master List Import'!$M$2:$M$700), 14) -> Grey Sweatpants (Lg) | I16: =INDEX('Master List Import'!$A$2:$P$700, MATCH('Auto Menu'!$G16, 'Master List Import'!$M$2:$M$700), 16) -> 25 | L16: 1202 | M16: =INDEX('Master List Import'!$A$2:$P$700, MATCH('Auto Menu'!$L16, 'Master List Import'!$M$2:$M$700), 14) -> White T-Shirt (Md) | N16: =INDEX('Master List Import'!$A$2:$P$700, MATCH('Auto Menu'!$L16, 'Master List Import'!$M$2:$M$700), 16) -> 5.05
B17: 1063 | C17: =INDEX('Master List Import'!$A$2:$P$700, MATCH('Auto Menu'!$B17, 'Master List Import'!$M$2:$M$700), 14) -> Grey Sweatshirt (XL) | D17: =INDEX('Master List Import'!$A$2:$P$700, MATCH('Auto Menu'!$B17, 'Master List Import'!$M$2:$M$700), 16) -> 21 | G17: 1073 | H17: =INDEX('Master List Import'!$A$2:$P$700, MATCH('Auto Menu'!$G17, 'Master List Import'!$M$2:$M$700), 14) -> Grey Sweatpants (XL) | I17: =INDEX('Master List Import'!$A$2:$P$700, MATCH('Auto Menu'!$G17, 'Master List Import'!$M$2:$M$700), 16) -> 25 | L17: 1203 | M17: =INDEX('Master List Import'!$A$2:$P$700, MATCH('Auto Menu'!$L17, 'Master List Import'!$M$2:$M$700), 14) -> White T-Shirt (Lg) | N17: =INDEX('Master List Import'!$A$2:$P$700, MATCH('Auto Menu'!$L17, 'Master List Import'!$M$2:$M$700), 16) -> 5.05
B18: 1064 | C18: =INDEX('Master List Import'!$A$2:$P$700, MATCH('Auto Menu'!$B18, 'Master List Import'!$M$2:$M$700), 14) -> Grey Sweatshirt (2X) | D18: =INDEX('Master List Import'!$A$2:$P$700, MATCH('Auto Menu'!$B18, 'Master List Import'!$M$2:$M$700), 16) -> 24 | G18: 1074 | H18: =INDEX('Master List Import'!$A$2:$P$700, MATCH('Auto Menu'!$G18, 'Master List Import'!$M$2:$M$700), 14) -> Grey Sweatpants (2X) | I18: =INDEX('Master List Import'!$A$2:$P$700, MATCH('Auto Menu'!$G18, 'Master List Import'!$M$2:$M$700), 16) -> 28 | L18: 1204 | M18: =INDEX('Master List Import'!$A$2:$P$700, MATCH('Auto Menu'!$L18, 'Master List Import'!$M$2:$M$700), 14) -> White T-Shirt (XL) | N18: =INDEX('Master List Import'!$A$2:$P$700, MATCH('Auto Menu'!$L18, 'Master List Import'!$M$2:$M$700), 16) -> 5.05
B19: 1065 | C19: =INDEX('Master List Import'!$A$2:$P$700, MATCH('Auto Menu'!$B19, 'Master List Import'!$M$2:$M$700), 14) -> Grey Sweatshirt (3X) | D19: =INDEX('Master List Import'!$A$2:$P$700, MATCH('Auto Menu'!$B19, 'Master List Import'!$M$2:$M$700), 16) -> 28 | G19: 1075 | H19: =INDEX('Master List Import'!$A$2:$P$700, MATCH('Auto Menu'!$G19, 'Master List Import'!$M$2:$M$700), 14) -> Grey Sweatpants (3X) | I19: =INDEX('Master List Import'!$A$2:$P$700, MATCH('Auto Menu'!$G19, 'Master List Import'!$M$2:$M$700), 16) -> 32 | L19: 1205 | M19: =INDEX('Master List Import'!$A$2:$P$700, MATCH('Auto Menu'!$L19, 'Master List Import'!$M$2:$M$700), 14) -> White T-Shirt (2X) | N19: =INDEX('Master List Import'!$A$2:$P$700, MATCH('Auto Menu'!$L19, 'Master List Import'!$M$2:$M$700), 16) -> 7.25
B20: 1066 | C20: =INDEX('Master List Import'!$A$2:$P$700, MATCH('Auto Menu'!$B20, 'Master List Import'!$M$2:$M$700), 14) -> Grey Sweatshirt (4X) | D20: =INDEX('Master List Import'!$A$2:$P$700, MATCH('Auto Menu'!$B20, 'Master List Import'!$M$2:$M$700), 16) -> 32 | G20: 1076 | H20: =INDEX('Master List Import'!$A$2:$P$700, MATCH('Auto Menu'!$G20, 'Master List Import'!$M$2:$M$700), 14) -> Grey Sweatpants (4X) | I20: =INDEX('Master List Import'!$A$2:$P$700, MATCH('Auto Menu'!$G20, 'Master List Import'!$M$2:$M$700), 16) -> 34.5 | L20: 1206 | M20: =INDEX('Master List Import'!$A$2:$P$700, MATCH('Auto Menu'!$L20, 'Master List Import'!$M$2:$M$700), 14) -> White T-Shirt (3X) | N20: =INDEX('Master List Import'!$A$2:$P$700, MATCH('Auto Menu'!$L20, 'Master List Import'!$M$2:$M$700), 16) -> 7.25
B21: 1067 | C21: =INDEX('Master List Import'!$A$2:$P$700, MATCH('Auto Menu'!$B21, 'Master List Import'!$M$2:$M$700), 14) -> Grey Sweatshirt (5XL) | D21: =INDEX('Master List Import'!$A$2:$P$700, MATCH('Auto Menu'!$B21, 'Master List Import'!$M$2:$M$700), 16) -> 33.5 | G21: 1077 | H21: =INDEX('Master List Import'!$A$2:$P$700, MATCH('Auto Menu'!$G21, 'Master List Import'!$M$2:$M$700), 14) -> Grey Sweatpants (5XL) | I21: =INDEX('Master List Import'!$A$2:$P$700, MATCH('Auto Menu'!$G21, 'Master List Import'!$M$2:$M$700), 16) -> 35.5 | L21: 1207 | M21: =INDEX('Master List Import'!$A$2:$P$700, MATCH('Auto Menu'!$L21, 'Master List Import'!$M$2:$M$700), 14) -> White T-Shirt (4X) | N21: =INDEX('Master List Import'!$A$2:$P$700, MATCH('Auto Menu'!$L21, 'Master List Import'!$M$2:$M$700), 16) -> 8.25
B22: 1068 | C22: =INDEX('Master List Import'!$A$2:$P$700, MATCH('Auto Menu'!$B22, 'Master List Import'!$M$2:$M$700), 14) -> Grey Sweatshirt (6XL) | D22: =INDEX('Master List Import'!$A$2:$P$700, MATCH('Auto Menu'!$B22, 'Master List Import'!$M$2:$M$700), 16) -> 36.5 | G22: 1078 | H22: =INDEX('Master List Import'!$A$2:$P$700, MATCH('Auto Menu'!$G22, 'Master List Import'!$M$2:$M$700), 14) -> Grey Sweatpants (6XL) | I22: =INDEX('Master List Import'!$A$2:$P$700, MATCH('Auto Menu'!$G22, 'Master List Import'!$M$2:$M$700), 16) -> 38.5 | L22: 1208 | M22: =INDEX('Master List Import'!$A$2:$P$700, MATCH('Auto Menu'!$L22, 'Master List Import'!$M$2:$M$700), 14) -> White T-Shirt (5X) | N22: =INDEX('Master List Import'!$A$2:$P$700, MATCH('Auto Menu'!$L22, 'Master List Import'!$M$2:$M$700), 16) -> 10.15
L23: 1209 | M23: =INDEX('Master List Import'!$A$2:$P$700, MATCH('Auto Menu'!$L23, 'Master List Import'!$M$2:$M$700), 14) -> White T-Shirt (6X) | N23: =INDEX('Master List Import'!$A$2:$P$700, MATCH('Auto Menu'!$L23, 'Master List Import'!$M$2:$M$700), 16) -> 12.15
A25: SOCKS | F25: MEN'S UNDERWEAR | K25: LINENS, LAUNDRY
B26: 1111 | C26: =INDEX('Master List Import'!$A$2:$P$700, MATCH('Auto Menu'!$B26, 'Master List Import'!$M$2:$M$700), 14) -> White Crew Socks | D26: =INDEX('Master List Import'!$A$2:$P$700, MATCH('Auto Menu'!$B26, 'Master List Import'!$M$2:$M$700), 16) -> 2.1 | G26: 1301 | H26: =INDEX('Master List Import'!$A$2:$P$700, MATCH('Auto Menu'!$G26, 'Master List Import'!$M$2:$M$700), 14) -> White Boxers (Sm) | I26: =INDEX('Master List Import'!$A$2:$P$700, MATCH('Auto Menu'!$G26, 'Master List Import'!$M$2:$M$700), 16) -> 4.3 | L26: 1900 | M26: =INDEX('Master List Import'!$A$2:$P$700, MATCH('Auto Menu'!$L26, 'Master List Import'!$M$2:$M$700), 14) -> White Bath Towel (Sm) | N26: =INDEX('Master List Import'!$A$2:$P$700, MATCH('Auto Menu'!$L26, 'Master List Import'!$M$2:$M$700), 16) -> 5.6
G27: 1302 | H27: =INDEX('Master List Import'!$A$2:$P$700, MATCH('Auto Menu'!$G27, 'Master List Import'!$M$2:$M$700), 14) -> White Boxers (Md) | I27: =INDEX('Master List Import'!$A$2:$P$700, MATCH('Auto Menu'!$G27, 'Master List Import'!$M$2:$M$700), 16) -> 4.3 | L27: 1901 | M27: =INDEX('Master List Import'!$A$2:$P$700, MATCH('Auto Menu'!$L27, 'Master List Import'!$M$2:$M$700), 14) -> White Bath Towel (Md) | N27: =INDEX('Master List Import'!$A$2:$P$700, MATCH('Auto Menu'!$L27, 'Master List Import'!$M$2:$M$700), 16) -> 5.8
A28: SHOES | G28: 1303 | H28: =INDEX('Master List Import'!$A$2:$P$700, MATCH('Auto Menu'!$G28, 'Master List Import'!$M$2:$M$700), 14) -> White Boxers (Lg) | I28: =INDEX('Master List Import'!$A$2:$P$700, MATCH('Auto Menu'!$G28, 'Master List Import'!$M$2:$M$700), 16) -> 4.3 | L28: 1910 | M28: =INDEX('Master List Import'!$A$2:$P$700, MATCH('Auto Menu'!$L28, 'Master List Import'!$M$2:$M$700), 14) -> Tan Bath Towel (Lg) | N28: =INDEX('Master List Import'!$A$2:$P$700, MATCH('Auto Menu'!$L28, 'Master List Import'!$M$2:$M$700), 16) -> 11
B29: 1602 | C29: =INDEX('Master List Import'!$A$2:$P$700, MATCH('Auto Menu'!$B29, 'Master List Import'!$M$2:$M$700), 14) -> Black Canvas Shoes (M07/L09) | D29: =INDEX('Master List Import'!$A$2:$P$700, MATCH('Auto Menu'!$B29, 'Master List Import'!$M$2:$M$700), 16) -> 15.55 | G29: 1304 | H29: =INDEX('Master List Import'!$A$2:$P$700, MATCH('Auto Menu'!$G29, 'Master List Import'!$M$2:$M$700), 14) -> White Boxers (XL) | I29: =INDEX('Master List Import'!$A$2:$P$700, MATCH('Auto Menu'!$G29, 'Master List Import'!$M$2:$M$700), 16) -> 4.3 | L29: 1920 | M29: =INDEX('Master List Import'!$A$2:$P$700, MATCH('Auto Menu'!$L29, 'Master List Import'!$M$2:$M$700), 14) -> Blue Bath Towel (Lg) | N29: =INDEX('Master List Import'!$A$2:$P$700, MATCH('Auto Menu'!$L29, 'Master List Import'!$M$2:$M$700), 16) -> 10.5
B30: 1603 | C30: =INDEX('Master List Import'!$A$2:$P$700, MATCH('Auto Menu'!$B30, 'Master List Import'!$M$2:$M$700), 14) -> Black Canvas Shoes (M08/L10) | D30: =INDEX('Master List Import'!$A$2:$P$700, MATCH('Auto Menu'!$B30, 'Master List Import'!$M$2:$M$700), 16) -> 15.55 | G30: 1305 | H30: =INDEX('Master List Import'!$A$2:$P$700, MATCH('Auto Menu'!$G30, 'Master List Import'!$M$2:$M$700), 14) -> White Boxers (2X) | I30: =INDEX('Master List Import'!$A$2:$P$700, MATCH('Auto Menu'!$G30, 'Master List Import'!$M$2:$M$700), 16) -> 4.8 | L30: 1800 | M30: =INDEX('Master List Import'!$A$2:$P$700, MATCH('Auto Menu'!$L30, 'Master List Import'!$M$2:$M$700), 14) -> White Washcloth | N30: =INDEX('Master List Import'!$A$2:$P$700, MATCH('Auto Menu'!$L30, 'Master List Import'!$M$2:$M$700), 16) -> 1
B31: 1604 | C31: =INDEX('Master List Import'!$A$2:$P$700, MATCH('Auto Menu'!$B31, 'Master List Import'!$M$2:$M$700), 14) -> Black Canvas Shoes (M09/L11) | D31: =INDEX('Master List Import'!$A$2:$P$700, MATCH('Auto Menu'!$B31, 'Master List Import'!$M$2:$M$700), 16) -> 15.55 | G31: 1306 | H31: =INDEX('Master List Import'!$A$2:$P$700, MATCH('Auto Menu'!$G31, 'Master List Import'!$M$2:$M$700), 14) -> White Boxers (3X) | I31: =INDEX('Master List Import'!$A$2:$P$700, MATCH('Auto Menu'!$G31, 'Master List Import'!$M$2:$M$700), 16) -> 5.8 | L31: 1810 | M31: =INDEX('Master List Import'!$A$2:$P$700, MATCH('Auto Menu'!$L31, 'Master List Import'!$M$2:$M$700), 14) -> Tan Washcloth | N31: =INDEX('Master List Import'!$A$2:$P$700, MATCH('Auto Menu'!$L31, 'Master List Import'!$M$2:$M$700), 16) -> 5
B32: 1605 | C32: =INDEX('Master List Import'!$A$2:$P$700, MATCH('Auto Menu'!$B32, 'Master List Import'!$M$2:$M$700), 14) -> Black Canvas Shoes (M10/L12) | D32: =INDEX('Master List Import'!$A$2:$P$700, MATCH('Auto Menu'!$B32, 'Master List Import'!$M$2:$M$700), 16) -> 15.55 | G32: 1307 | H32: =INDEX('Master List Import'!$A$2:$P$700, MATCH('Auto Menu'!$G32, 'Master List Import'!$M$2:$M$700), 14) -> White Boxers (4X) | I32: =INDEX('Master List Import'!$A$2:$P$700, MATCH('Auto Menu'!$G32, 'Master List Import'!$M$2:$M$700), 16) -> 6.05 | L32: 1820 | M32: =INDEX('Master List Import'!$A$2:$P$700, MATCH('Auto Menu'!$L32, 'Master List Import'!$M$2:$M$700), 14) -> Blue Washcloth | N32: =INDEX('Master List Import'!$A$2:$P$700, MATCH('Auto Menu'!$L32, 'Master List Import'!$M$2:$M$700), 16) -> 2.1
B33: 1606 | C33: =INDEX('Master List Import'!$A$2:$P$700, MATCH('Auto Menu'!$B33, 'Master List Import'!$M$2:$M$700), 14) -> Black Canvas Shoes (M11) | D33: =INDEX('Master List Import'!$A$2:$P$700, MATCH('Auto Menu'!$B33, 'Master List Import'!$M$2:$M$700), 16) -> 15.55 | G33: 1308 | H33: =INDEX('Master List Import'!$A$2:$P$700, MATCH('Auto Menu'!$G33, 'Master List Import'!$M$2:$M$700), 14) -> White Boxers (5X) | I33: =INDEX('Master List Import'!$A$2:$P$700, MATCH('Auto Menu'!$G33, 'Master List Import'!$M$2:$M$700), 16) -> 6.8 | L33: 2000 | M33: =INDEX('Master List Import'!$A$2:$P$700, MATCH('Auto Menu'!$L33, 'Master List Import'!$M$2:$M$700), 14) -> Mesh Laundry Bag | N33: =INDEX('Master List Import'!$A$2:$P$700, MATCH('Auto Menu'!$L33, 'Master List Import'!$M$2:$M$700), 16) -> 7.5
B34: 1607 | C34: =INDEX('Master List Import'!$A$2:$P$700, MATCH('Auto Menu'!$B34, 'Master List Import'!$M$2:$M$700), 14) -> Black Canvas Shoes (M12) | D34: =INDEX('Master List Import'!$A$2:$P$700, MATCH('Auto Menu'!$B34, 'Master List Import'!$M$2:$M$700), 16) -> 15.55 | G34: 1309 | H34: =INDEX('Master List Import'!$A$2:$P$700, MATCH('Auto Menu'!$G34, 'Master List Import'!$M$2:$M$700), 14) -> White Boxers (6X) | I34: =INDEX('Master List Import'!$A$2:$P$700, MATCH('Auto Menu'!$G34, 'Master List Import'!$M$2:$M$700), 16) -> 7.5
B35: 1608 | C35: =INDEX('Master List Import'!$A$2:$P$700, MATCH('Auto Menu'!$B35, 'Master List Import'!$M$2:$M$700), 14) -> Black Canvas Shoes (M13) | D35: =INDEX('Master List Import'!$A$2:$P$700, MATCH('Auto Menu'!$B35, 'Master List Import'!$M$2:$M$700), 16) -> 15.55
B36: 1609 | C36: =INDEX('Master List Import'!$A$2:$P$700, MATCH('Auto Menu'!$B36, 'Master List Import'!$M$2:$M$700), 14) -> Black Canvas Shoes (M14) | D36: =INDEX('Master List Import'!$A$2:$P$700, MATCH('Auto Menu'!$B36, 'Master List Import'!$M$2:$M$700), 16) -> 15.55
B37: 1610 | C37: =INDEX('Master List Import'!$A$2:$P$700, MATCH('Auto Menu'!$B37, 'Master List Import'!$M$2:$M$700), 14) -> Black Canvas Shoes (M15) | D37: =INDEX('Master List Import'!$A$2:$P$700, MATCH('Auto Menu'!$B37, 'Master List Import'!$M$2:$M$700), 16) -> 15.55 | F37: WOMEN'S UNDERWEAR
B38: 1703 | C38: =INDEX('Master List Import'!$A$2:$P$700, MATCH('Auto Menu'!$B38, 'Master List Import'!$M$2:$M$700), 14) -> Shower Sandals (08) | D38: =INDEX('Master List Import'!$A$2:$P$700, MATCH('Auto Menu'!$B38, 'Master List Import'!$M$2:$M$700), 16) -> 8 | G38: 1400 | H38: =INDEX('Master List Import'!$A$2:$P$700, MATCH('Auto Menu'!$G38, 'Master List Import'!$M$2:$M$700), 14) -> White Panties (Sz 05) | I38: =INDEX('Master List Import'!$A$2:$P$700, MATCH('Auto Menu'!$G38, 'Master List Import'!$M$2:$M$700), 16) -> 2.95
B39: 1705 | C39: =INDEX('Master List Import'!$A$2:$P$700, MATCH('Auto Menu'!$B39, 'Master List Import'!$M$2:$M$700), 14) -> Shower Sandals (10) | D39: =INDEX('Master List Import'!$A$2:$P$700, MATCH('Auto Menu'!$B39, 'Master List Import'!$M$2:$M$700), 16) -> 8 | G39: 1401 | H39: =INDEX('Master List Import'!$A$2:$P$700, MATCH('Auto Menu'!$G39, 'Master List Import'!$M$2:$M$700), 14) -> White Panties (Sz 06) | I39: =INDEX('Master List Import'!$A$2:$P$700, MATCH('Auto Menu'!$G39, 'Master List Import'!$M$2:$M$700), 16) -> 2.95
B40: 1707 | C40: =INDEX('Master List Import'!$A$2:$P$700, MATCH('Auto Menu'!$B40, 'Master List Import'!$M$2:$M$700), 14) -> Shower Sandals (12) | D40: =INDEX('Master List Import'!$A$2:$P$700, MATCH('Auto Menu'!$B40, 'Master List Import'!$M$2:$M$700), 16) -> 8 | G40: 1402 | H40: =INDEX('Master List Import'!$A$2:$P$700, MATCH('Auto Menu'!$G40, 'Master List Import'!$M$2:$M$700), 14) -> White Panties (Sz 07) | I40: =INDEX('Master List Import'!$A$2:$P$700, MATCH('Auto Menu'!$G40, 'Master List Import'!$M$2:$M$700), 16) -> 2.95
B41: 1708 | C41: =INDEX('Master List Import'!$A$2:$P$700, MATCH('Auto Menu'!$B41, 'Master List Import'!$M$2:$M$700), 14) -> Shower Sandals (14) | D41: =INDEX('Master List Import'!$A$2:$P$700, MATCH('Auto Menu'!$B41, 'Master List Import'!$M$2:$M$700), 16) -> 8 | G41: 1403 | H41: =INDEX('Master List Import'!$A$2:$P$700, MATCH('Auto Menu'!$G41, 'Master List Import'!$M$2:$M$700), 14) -> White Panties (Sz 08) | I41: =INDEX('Master List Import'!$A$2:$P$700, MATCH('Auto Menu'!$G41, 'Master List Import'!$M$2:$M$700), 16) -> 2.95
B42: 1710 | C42: =INDEX('Master List Import'!$A$2:$P$700, MATCH('Auto Menu'!$B42, 'Master List Import'!$M$2:$M$700), 14) -> Shower Sandals (17) | D42: =INDEX('Master List Import'!$A$2:$P$700, MATCH('Auto Menu'!$B42, 'Master List Import'!$M$2:$M$700), 16) -> 8 | G42: 1404 | H42: =INDEX('Master List Import'!$A$2:$P$700, MATCH('Auto Menu'!$G42, 'Master List Import'!$M$2:$M$700), 14) -> White Panties (Sz 09) | I42: =INDEX('Master List Import'!$A$2:$P$700, MATCH('Auto Menu'!$G42, 'Master List Import'!$M$2:$M$700), 16) -> 3.05
B43: 1622 | C43: =INDEX('Master List Import'!$A$2:$P$700, MATCH('Auto Menu'!$B43, 'Master List Import'!$M$2:$M$700), 14) -> Orange Canvas Shoes (M07/L09) | D43: =INDEX('Master List Import'!$A$2:$P$700, MATCH('Auto Menu'!$B43, 'Master List Import'!$M$2:$M$700), 16) -> 15.55 | G43: 1405 | H43: =INDEX('Master List Import'!$A$2:$P$700, MATCH('Auto Menu'!$G43, 'Master List Import'!$M$2:$M$700), 14) -> White Panties (Sz 10) | I43: =INDEX('Master List Import'!$A$2:$P$700, MATCH('Auto Menu'!$G43, 'Master List Import'!$M$2:$M$700), 16) -> 3.3
B44: 1623 | C44: =INDEX('Master List Import'!$A$2:$P$700, MATCH('Auto Menu'!$B44, 'Master List Import'!$M$2:$M$700), 14) -> Orange Canvas Shoes (M08/L10) | D44: =INDEX('Master List Import'!$A$2:$P$700, MATCH('Auto Menu'!$B44, 'Master List Import'!$M$2:$M$700), 16) -> 15.55 | G44: 1406 | H44: =INDEX('Master List Import'!$A$2:$P$700, MATCH('Auto Menu'!$G44, 'Master List Import'!$M$2:$M$700), 14) -> White Panties (Sz 11) | I44: =INDEX('Master List Import'!$A$2:$P$700, MATCH('Auto Menu'!$G44, 'Master List Import'!$M$2:$M$700), 16) -> 3.3
B45: 1624 | C45: =INDEX('Master List Import'!$A$2:$P$700, MATCH('Auto Menu'!$B45, 'Master List Import'!$M$2:$M$700), 14) -> Orange Canvas Shoes (M09/L11) | D45: =INDEX('Master List Import'!$A$2:$P$700, MATCH('Auto Menu'!$B45, 'Master List Import'!$M$2:$M$700), 16) -> 15.55 | G45: 1407 | H45: =INDEX('Master List Import'!$A$2:$P$700, MATCH('Auto Menu'!$G45, 'Master List Import'!$M$2:$M$700), 14) -> White Panties (Sz 12) | I45: =INDEX('Master List Import'!$A$2:$P$700, MATCH('Auto Menu'!$G45, 'Master List Import'!$M$2:$M$700), 16) -> 3.3
B46: 1625 | C46: =INDEX('Master List Import'!$A$2:$P$700, MATCH('Auto Menu'!$B46, 'Master List Import'!$M$2:$M$700), 14) -> Orange Canvas Shoes (M10/L12) | D46: =INDEX('Master List Import'!$A$2:$P$700, MATCH('Auto Menu'!$B46, 'Master List Import'!$M$2:$M$700), 16) -> 15.55 | G46: 1408 | H46: =INDEX('Master List Import'!$A$2:$P$700, MATCH('Auto Menu'!$G46, 'Master List Import'!$M$2:$M$700), 14) -> White Panties (Sz 13) | I46: =INDEX('Master List Import'!$A$2:$P$700, MATCH('Auto Menu'!$G46, 'Master List Import'!$M$2:$M$700), 16) -> 4.5
B47: 1626 | C47: =INDEX('Master List Import'!$A$2:$P$700, MATCH('Auto Menu'!$B47, 'Master List Import'!$M$2:$M$700), 14) -> Orange Canvas Shoes (M11) | D47: =INDEX('Master List Import'!$A$2:$P$700, MATCH('Auto Menu'!$B47, 'Master List Import'!$M$2:$M$700), 16) -> 15.55 | G47: 1409 | H47: =INDEX('Master List Import'!$A$2:$P$700, MATCH('Auto Menu'!$G47, 'Master List Import'!$M$2:$M$700), 14) -> White Panties (Sz 14) | I47: =INDEX('Master List Import'!$A$2:$P$700, MATCH('Auto Menu'!$G47, 'Master List Import'!$M$2:$M$700), 16) -> 5.5
B48: 1627 | C48: =INDEX('Master List Import'!$A$2:$P$700, MATCH('Auto Menu'!$B48, 'Master List Import'!$M$2:$M$700), 14) -> Orange Canvas Shoes (M12) | D48: =INDEX('Master List Import'!$A$2:$P$700, MATCH('Auto Menu'!$B48, 'Master List Import'!$M$2:$M$700), 16) -> 15.55 | G48: 1500 | H48: =INDEX('Master List Import'!$A$2:$P$700, MATCH('Auto Menu'!$G48, 'Master List Import'!$M$2:$M$700), 14) -> White Sports Bra (32) | I48: =INDEX('Master List Import'!$A$2:$P$700, MATCH('Auto Menu'!$G48, 'Master List Import'!$M$2:$M$700), 16) -> 8.3
B49: 1628 | C49: =INDEX('Master List Import'!$A$2:$P$700, MATCH('Auto Menu'!$B49, 'Master List Import'!$M$2:$M$700), 14) -> Orange Canvas Shoes (M13) | D49: =INDEX('Master List Import'!$A$2:$P$700, MATCH('Auto Menu'!$B49, 'Master List Import'!$M$2:$M$700), 16) -> 15.55 | G49: 1501 | H49: =INDEX('Master List Import'!$A$2:$P$700, MATCH('Auto Menu'!$G49, 'Master List Import'!$M$2:$M$700), 14) -> White Sports Bra (34) | I49: =INDEX('Master List Import'!$A$2:$P$700, MATCH('Auto Menu'!$G49, 'Master List Import'!$M$2:$M$700), 16) -> 8.3
... B54: 1638 | C54: =INDEX('Master List Import'!$A$2:$P$700, MATCH('Auto Menu'!$B54, 'Master List Import'!$M$2:$M$700), 14) -> White Athletic Lace-up Shoes (12) | D54: =INDEX('Master List Import'!$A$2:$P$700, MATCH('Auto Menu'!$B54, 'Master List Import'!$M$2:$M$700), 16) -> 40 | G54: 1509 | H54: =INDEX('Master List Import'!$A$2:$P$700, MATCH('Auto Menu'!$G54, 'Master List Import'!$M$2:$M$700), 14) -> White Sports Bra (50) | I54: =INDEX('Master List Import'!$A$2:$P$700, MATCH('Auto Menu'!$G54, 'Master List Import'!$M$2:$M$700), 16) -> 10.5
A56: EYE CARE, MEDICINE, & HEALTH
A57: EYE CARE | F57: MEDICINE | K57: HEALTH
B58: 5600 | C58: =INDEX('Master List Import'!$A$2:$P$700, MATCH('Auto Menu'!$B58, 'Master List Import'!$M$2:$M$700), 14) -> Contact Lens Case | D58: =INDEX('Master List Import'!$A$2:$P$700, MATCH('Auto Menu'!$B58, 'Master List Import'!$M$2:$M$700), 16) -> 3.65 | G58: 5700 | H58: =INDEX('Master List Import'!$A$2:$P$700, MATCH('Auto Menu'!$G58, 'Master List Import'!$M$2:$M$700), 14) -> Acetaminophen (2pk) | I58: =INDEX('Master List Import'!$A$2:$P$700, MATCH('Auto Menu'!$G58, 'Master List Import'!$M$2:$M$700), 16) -> 1 | L58: 5720 | M58: =INDEX('Master List Import'!$A$2:$P$700, MATCH('Auto Menu'!$L58, 'Master List Import'!$M$2:$M$700), 14) -> Rolaids | N58: =INDEX('Master List Import'!$A$2:$P$700, MATCH('Auto Menu'!$L58, 'Master List Import'!$M$2:$M$700), 16) -> 2.05
B59: 5610 | C59: =INDEX('Master List Import'!$A$2:$P$700, MATCH('Auto Menu'!$B59, 'Master List Import'!$M$2:$M$700), 14) -> Contact Lens Solution | D59: =INDEX('Master List Import'!$A$2:$P$700, MATCH('Auto Menu'!$B59, 'Master List Import'!$M$2:$M$700), 16) -> 5.5 | G59: 5701 | H59: =INDEX('Master List Import'!$A$2:$P$700, MATCH('Auto Menu'!$G59, 'Master List Import'!$M$2:$M$700), 14) -> Ibuprofen (2pk) | I59: =INDEX('Master List Import'!$A$2:$P$700, MATCH('Auto Menu'!$G59, 'Master List Import'!$M$2:$M$700), 16) -> 0.7 | L59: 5730 | M59: =INDEX('Master List Import'!$A$2:$P$700, MATCH('Auto Menu'!$L59, 'Master List Import'!$M$2:$M$700), 14) -> Halls Menthol Cough Drops | N59: =INDEX('Master List Import'!$A$2:$P$700, MATCH('Auto Menu'!$L59, 'Master List Import'!$M$2:$M$700), 16) -> 2.25
B60: 5620 | C60: =INDEX('Master List Import'!$A$2:$P$700, MATCH('Auto Menu'!$B60, 'Master List Import'!$M$2:$M$700), 14) -> Artificial Tears Eye Drops | D60: =INDEX('Master List Import'!$A$2:$P$700, MATCH('Auto Menu'!$B60, 'Master List Import'!$M$2:$M$700), 16) -> 3.2 | G60: 5710 | H60: =INDEX('Master List Import'!$A$2:$P$700, MATCH('Auto Menu'!$G60, 'Master List Import'!$M$2:$M$700), 14) -> Alka Seltzer (2pk) | I60: =INDEX('Master List Import'!$A$2:$P$700, MATCH('Auto Menu'!$G60, 'Master List Import'!$M$2:$M$700), 16) -> 0.9 | L60: 5731 | M60: =INDEX('Master List Import'!$A$2:$P$700, MATCH('Auto Menu'!$L60, 'Master List Import'!$M$2:$M$700), 14) -> Halls Cherry Cough Drops | N60: =INDEX('Master List Import'!$A$2:$P$700, MATCH('Auto Menu'!$L60, 'Master List Import'!$M$2:$M$700), 16) -> 2.25
B61: 5630 | C61: =INDEX('Master List Import'!$A$2:$P$700, MATCH('Auto Menu'!$B61, 'Master List Import'!$M$2:$M$700), 14) -> Reading Glasses (1.00) | D61: =INDEX('Master List Import'!$A$2:$P$700, MATCH('Auto Menu'!$B61, 'Master List Import'!$M$2:$M$700), 16) -> 8.7 | G61: 5711 | H61: =INDEX('Master List Import'!$A$2:$P$700, MATCH('Auto Menu'!$G61, 'Master List Import'!$M$2:$M$700), 14) -> Cold & Sinus (2pk) | I61: =INDEX('Master List Import'!$A$2:$P$700, MATCH('Auto Menu'!$G61, 'Master List Import'!$M$2:$M$700), 16) -> 0.7 | L61: 5800 | M61: =INDEX('Master List Import'!$A$2:$P$700, MATCH('Auto Menu'!$L61, 'Master List Import'!$M$2:$M$700), 14) -> Multivitamins (100ct) | N61: =INDEX('Master List Import'!$A$2:$P$700, MATCH('Auto Menu'!$L61, 'Master List Import'!$M$2:$M$700), 16) -> 6
B62: 5631 | C62: =INDEX('Master List Import'!$A$2:$P$700, MATCH('Auto Menu'!$B62, 'Master List Import'!$M$2:$M$700), 14) -> Reading Glasses (1.25) | D62: =INDEX('Master List Import'!$A$2:$P$700, MATCH('Auto Menu'!$B62, 'Master List Import'!$M$2:$M$700), 16) -> 8.7 | G62: 5712 | H62: =INDEX('Master List Import'!$A$2:$P$700, MATCH('Auto Menu'!$G62, 'Master List Import'!$M$2:$M$700), 14) -> Diphen Allergy Relief (2pk) | I62: =INDEX('Master List Import'!$A$2:$P$700, MATCH('Auto Menu'!$G62, 'Master List Import'!$M$2:$M$700), 16) -> 0.7
B63: 5632 | C63: =INDEX('Master List Import'!$A$2:$P$700, MATCH('Auto Menu'!$B63, 'Master List Import'!$M$2:$M$700), 14) -> Reading Glasses (1.50) | D63: =INDEX('Master List Import'!$A$2:$P$700, MATCH('Auto Menu'!$B63, 'Master List Import'!$M$2:$M$700), 16) -> 8.7
B64: 5633 | C64: =INDEX('Master List Import'!$A$2:$P$700, MATCH('Auto Menu'!$B64, 'Master List Import'!$M$2:$M$700), 14) -> Reading Glasses (1.75) | D64: =INDEX('Master List Import'!$A$2:$P$700, MATCH('Auto Menu'!$B64, 'Master List Import'!$M$2:$M$700), 16) -> 8.7
B65: 5634 | C65: =INDEX('Master List Import'!$A$2:$P$700, MATCH('Auto Menu'!$B65, 'Master List Import'!$M$2:$M$700), 14) -> Reading Glasses (2.00) | D65: =INDEX('Master List Import'!$A$2:$P$700, MATCH('Auto Menu'!$B65, 'Master List Import'!$M$2:$M$700), 16) -> 8.7
B66: 5635 | C66: =INDEX('Master List Import'!$A$2:$P$700, MATCH('Auto Menu'!$B66, 'Master List Import'!$M$2:$M$700), 14) -> Reading Glasses (2.25) | D66: =INDEX('Master List Import'!$A$2:$P$700, MATCH('Auto Menu'!$B66, 'Master List Import'!$M$2:$M$700), 16) -> 8.7
B67: 5636 | C67: =INDEX('Master List Import'!$A$2:$P$700, MATCH('Auto Menu'!$B67, 'Master List Import'!$M$2:$M$700), 14) -> Reading Glasses (2.50) | D67: =INDEX('Master List Import'!$A$2:$P$700, MATCH('Auto Menu'!$B67, 'Master List Import'!$M$2:$M$700), 16) -> 8.7
B68: 5637 | C68: =INDEX('Master List Import'!$A$2:$P$700, MATCH('Auto Menu'!$B68, 'Master List Import'!$M$2:$M$700), 14) -> Reading Glasses (2.75) | D68: =INDEX('Master List Import'!$A$2:$P$700, MATCH('Auto Menu'!$B68, 'Master List Import'!$M$2:$M$700), 16) -> 8.7
B69: 5638 | C69: =INDEX('Master List Import'!$A$2:$P$700, MATCH('Auto Menu'!$B69, 'Master List Import'!$M$2:$M$700), 14) -> Reading Glasses (3.00) | D69: =INDEX('Master List Import'!$A$2:$P$700, MATCH('Auto Menu'!$B69, 'Master List Import'!$M$2:$M$700), 16) -> 8.7
B70: 5639 | C70: =INDEX('Master List Import'!$A$2:$P$700, MATCH('Auto Menu'!$B70, 'Master List Import'!$M$2:$M$700), 14) -> Reading Glasses (3.25) | D70: =INDEX('Master List Import'!$A$2:$P$700, MATCH('Auto Menu'!$B70, 'Master List Import'!$M$2:$M$700), 16) -> 8.7
B71: 5640 | C71: =INDEX('Master List Import'!$A$2:$P$700, MATCH('Auto Menu'!$B71, 'Master List Import'!$M$2:$M$700), 14) -> Reading Glasses (3.50) | D71: =INDEX('Master List Import'!$A$2:$P$700, MATCH('Auto Menu'!$B71, 'Master List Import'!$M$2:$M$700), 16) -> 8.7
A81: HYGIENE, TOILETRY, & PERSONAL CARE
A82: SOAP | F82: HAIR CARE | K82: PERSONAL CARE
B83: 4100 | C83: =INDEX('Master List Import'!$A$2:$P$700, MATCH('Auto Menu'!$B83, 'Master List Import'!$M$2:$M$700), 14) -> Dalan Bar Soap | D83: =INDEX('Master List Import'!$A$2:$P$700, MATCH('Auto Menu'!$B83, 'Master List Import'!$M$2:$M$700), 16) -> 1.65 | G83: 5100 | H83: =INDEX('Master List Import'!$A$2:$P$700, MATCH('Auto Menu'!$G83, 'Master List Import'!$M$2:$M$700), 14) -> Pocket Comb (5") | I83: =INDEX('Master List Import'!$A$2:$P$700, MATCH('Auto Menu'!$G83, 'Master List Import'!$M$2:$M$700), 16) -> 0.25 | L83: 1850 | M83: =INDEX('Master List Import'!$A$2:$P$700, MATCH('Auto Menu'!$L83, 'Master List Import'!$M$2:$M$700), 14) -> Mesh Bath Pouf | N83: =INDEX('Master List Import'!$A$2:$P$700, MATCH('Auto Menu'!$L83, 'Master List Import'!$M$2:$M$700), 16) -> 2.75
B84: 4101 | C84: =INDEX('Master List Import'!$A$2:$P$700, MATCH('Auto Menu'!$B84, 'Master List Import'!$M$2:$M$700), 14) -> Jergens Bar Soap | D84: =INDEX('Master List Import'!$A$2:$P$700, MATCH('Auto Menu'!$B84, 'Master List Import'!$M$2:$M$700), 16) -> 1.8 | G84: 5101 | H84: =INDEX('Master List Import'!$A$2:$P$700, MATCH('Auto Menu'!$G84, 'Master List Import'!$M$2:$M$700), 14) -> Large Comb (8") | I84: =INDEX('Master List Import'!$A$2:$P$700, MATCH('Auto Menu'!$G84, 'Master List Import'!$M$2:$M$700), 16) -> 0.5 | L84: 4300 | M84: =INDEX('Master List Import'!$A$2:$P$700, MATCH('Auto Menu'!$L84, 'Master List Import'!$M$2:$M$700), 14) -> Shaving Cream | N84: =INDEX('Master List Import'!$A$2:$P$700, MATCH('Auto Menu'!$L84, 'Master List Import'!$M$2:$M$700), 16) -> 1.85
B85: 4102 | C85: =INDEX('Master List Import'!$A$2:$P$700, MATCH('Auto Menu'!$B85, 'Master List Import'!$M$2:$M$700), 14) -> Irish Spring Bar Soap | D85: =INDEX('Master List Import'!$A$2:$P$700, MATCH('Auto Menu'!$B85, 'Master List Import'!$M$2:$M$700), 16) -> 2 | G85: 5110 | H85: =INDEX('Master List Import'!$A$2:$P$700, MATCH('Auto Menu'!$G85, 'Master List Import'!$M$2:$M$700), 14) -> Palm Brush | I85: =INDEX('Master List Import'!$A$2:$P$700, MATCH('Auto Menu'!$G85, 'Master List Import'!$M$2:$M$700), 16) -> 2.65 | L85: 4301 | M85: =INDEX('Master List Import'!$A$2:$P$700, MATCH('Auto Menu'!$L85, 'Master List Import'!$M$2:$M$700), 14) -> Magic Shave Cream | N85: =INDEX('Master List Import'!$A$2:$P$700, MATCH('Auto Menu'!$L85, 'Master List Import'!$M$2:$M$700), 16) -> 9
B86: 4103 | C86: =INDEX('Master List Import'!$A$2:$P$700, MATCH('Auto Menu'!$B86, 'Master List Import'!$M$2:$M$700), 14) -> Freshscent Bar Soap | D86: =INDEX('Master List Import'!$A$2:$P$700, MATCH('Auto Menu'!$B86, 'Master List Import'!$M$2:$M$700), 16) -> 1.25 | G86: 5120 | H86: =INDEX('Master List Import'!$A$2:$P$700, MATCH('Auto Menu'!$G86, 'Master List Import'!$M$2:$M$700), 14) -> Ponytail Holders (18pk) | I86: =INDEX('Master List Import'!$A$2:$P$700, MATCH('Auto Menu'!$G86, 'Master List Import'!$M$2:$M$700), 16) -> 2.8 | L86: 4310 | M86: =INDEX('Master List Import'!$A$2:$P$700, MATCH('Auto Menu'!$L86, 'Master List Import'!$M$2:$M$700), 14) -> After Shave Lotion | N86: =INDEX('Master List Import'!$A$2:$P$700, MATCH('Auto Menu'!$L86, 'Master List Import'!$M$2:$M$700), 16) -> 1.85
B87: 4104 | C87: =INDEX('Master List Import'!$A$2:$P$700, MATCH('Auto Menu'!$B87, 'Master List Import'!$M$2:$M$700), 14) -> Dial Gold Soap | D87: =INDEX('Master List Import'!$A$2:$P$700, MATCH('Auto Menu'!$B87, 'Master List Import'!$M$2:$M$700), 16) -> 2.4 | G87: 5121 | H87: =INDEX('Master List Import'!$A$2:$P$700, MATCH('Auto Menu'!$G87, 'Master List Import'!$M$2:$M$700), 14) -> Hair Scrunchy | I87: =INDEX('Master List Import'!$A$2:$P$700, MATCH('Auto Menu'!$G87, 'Master List Import'!$M$2:$M$700), 16) -> 2.25 | L87: 5400 | M87: =INDEX('Master List Import'!$A$2:$P$700, MATCH('Auto Menu'!$L87, 'Master List Import'!$M$2:$M$700), 14) -> Petroleum Jelly | N87: =INDEX('Master List Import'!$A$2:$P$700, MATCH('Auto Menu'!$L87, 'Master List Import'!$M$2:$M$700), 16) -> 2.1
B88: 4108 | C88: =INDEX('Master List Import'!$A$2:$P$700, MATCH('Auto Menu'!$B88, 'Master List Import'!$M$2:$M$700), 14) -> Ambi Cocoa Butter Soap | D88: =INDEX('Master List Import'!$A$2:$P$700, MATCH('Auto Menu'!$B88, 'Master List Import'!$M$2:$M$700), 16) -> 5.6 | G88: 5130 | H88: =INDEX('Master List Import'!$A$2:$P$700, MATCH('Auto Menu'!$G88, 'Master List Import'!$M$2:$M$700), 14) -> Durag | I88: =INDEX('Master List Import'!$A$2:$P$700, MATCH('Auto Menu'!$G88, 'Master List Import'!$M$2:$M$700), 16) -> 5 | L88: 5410 | M88: =INDEX('Master List Import'!$A$2:$P$700, MATCH('Auto Menu'!$L88, 'Master List Import'!$M$2:$M$700), 14) -> Baby Oil | N88: =INDEX('Master List Import'!$A$2:$P$700, MATCH('Auto Menu'!$L88, 'Master List Import'!$M$2:$M$700), 16) -> 1.9
B89: 4150 | C89: =INDEX('Master List Import'!$A$2:$P$700, MATCH('Auto Menu'!$B89, 'Master List Import'!$M$2:$M$700), 14) -> Soap Dish | D89: =INDEX('Master List Import'!$A$2:$P$700, MATCH('Auto Menu'!$B89, 'Master List Import'!$M$2:$M$700), 16) -> 0.75 | G89: 5200 | H89: =INDEX('Master List Import'!$A$2:$P$700, MATCH('Auto Menu'!$G89, 'Master List Import'!$M$2:$M$700), 14) -> Murray's Hair Pomade | I89: =INDEX('Master List Import'!$A$2:$P$700, MATCH('Auto Menu'!$G89, 'Master List Import'!$M$2:$M$700), 16) -> 6 | L89: 5420 | M89: =INDEX('Master List Import'!$A$2:$P$700, MATCH('Auto Menu'!$L89, 'Master List Import'!$M$2:$M$700), 14) -> Cocoa Butter Skin Lotion | N89: =INDEX('Master List Import'!$A$2:$P$700, MATCH('Auto Menu'!$L89, 'Master List Import'!$M$2:$M$700), 16) -> 3.05
G90: 5201 | H90: =INDEX('Master List Import'!$A$2:$P$700, MATCH('Auto Menu'!$G90, 'Master List Import'!$M$2:$M$700), 14) -> Royal Crown Hair Dressing | I90: =INDEX('Master List Import'!$A$2:$P$700, MATCH('Auto Menu'!$G90, 'Master List Import'!$M$2:$M$700), 16) -> 4.55 | L90: 5421 | M90: =INDEX('Master List Import'!$A$2:$P$700, MATCH('Auto Menu'!$L90, 'Master List Import'!$M$2:$M$700), 14) -> Vitamin E Skin Lotion | N90: =INDEX('Master List Import'!$A$2:$P$700, MATCH('Auto Menu'!$L90, 'Master List Import'!$M$2:$M$700), 16) -> 3.05
A91: DEODORANT | G91: 5202 | H91: =INDEX('Master List Import'!$A$2:$P$700, MATCH('Auto Menu'!$G91, 'Master List Import'!$M$2:$M$700), 14) -> DEP Styling Gel | I91: =INDEX('Master List Import'!$A$2:$P$700, MATCH('Auto Menu'!$G91, 'Master List Import'!$M$2:$M$700), 16) -> 2.5 | L91: 5422 | M91: =INDEX('Master List Import'!$A$2:$P$700, MATCH('Auto Menu'!$L91, 'Master List Import'!$M$2:$M$700), 14) -> Aloe Vera Skin Lotion | N91: =INDEX('Master List Import'!$A$2:$P$700, MATCH('Auto Menu'!$L91, 'Master List Import'!$M$2:$M$700), 16) -> 3.05
B92: 4200 | C92: =INDEX('Master List Import'!$A$2:$P$700, MATCH('Auto Menu'!$B92, 'Master List Import'!$M$2:$M$700), 14) -> Dial Roll-On Deodorant | D92: =INDEX('Master List Import'!$A$2:$P$700, MATCH('Auto Menu'!$B92, 'Master List Import'!$M$2:$M$700), 16) -> 2.8 | G92: 5210 | H92: =INDEX('Master List Import'!$A$2:$P$700, MATCH('Auto Menu'!$G92, 'Master List Import'!$M$2:$M$700), 14) -> Dark & Lovely Relaxer | I92: =INDEX('Master List Import'!$A$2:$P$700, MATCH('Auto Menu'!$G92, 'Master List Import'!$M$2:$M$700), 16) -> 19 | L92: 5423 | M92: =INDEX('Master List Import'!$A$2:$P$700, MATCH('Auto Menu'!$L92, 'Master List Import'!$M$2:$M$700), 14) -> Sunscreen (SPF 30) | N92: =INDEX('Master List Import'!$A$2:$P$700, MATCH('Auto Menu'!$L92, 'Master List Import'!$M$2:$M$700), 16) -> 8
B93: 4201 | C93: =INDEX('Master List Import'!$A$2:$P$700, MATCH('Auto Menu'!$B93, 'Master List Import'!$M$2:$M$700), 14) -> Freshscent Roll-On Deodorant | D93: =INDEX('Master List Import'!$A$2:$P$700, MATCH('Auto Menu'!$B93, 'Master List Import'!$M$2:$M$700), 16) -> 1.15 | G93: 5211 | H93: =INDEX('Master List Import'!$A$2:$P$700, MATCH('Auto Menu'!$G93, 'Master List Import'!$M$2:$M$700), 14) -> Lusti Hair Food | I93: =INDEX('Master List Import'!$A$2:$P$700, MATCH('Auto Menu'!$G93, 'Master List Import'!$M$2:$M$700), 16) -> 2.5 | L93: 5424 | M93: =INDEX('Master List Import'!$A$2:$P$700, MATCH('Auto Menu'!$L93, 'Master List Import'!$M$2:$M$700), 14) -> Lubriderm Lotion | N93: =INDEX('Master List Import'!$A$2:$P$700, MATCH('Auto Menu'!$L93, 'Master List Import'!$M$2:$M$700), 16) -> 11
B94: 4210 | C94: =INDEX('Master List Import'!$A$2:$P$700, MATCH('Auto Menu'!$B94, 'Master List Import'!$M$2:$M$700), 14) -> Lady Speed Stick, Shower Fresh | D94: =INDEX('Master List Import'!$A$2:$P$700, MATCH('Auto Menu'!$B94, 'Master List Import'!$M$2:$M$700), 16) -> 4.5 | G94: 5212 | H94: =INDEX('Master List Import'!$A$2:$P$700, MATCH('Auto Menu'!$G94, 'Master List Import'!$M$2:$M$700), 14) -> Luster's Pink Oil Hair Moisturizer | I94: =INDEX('Master List Import'!$A$2:$P$700, MATCH('Auto Menu'!$G94, 'Master List Import'!$M$2:$M$700), 16) -> 12 | L94: 5430 | M94: =INDEX('Master List Import'!$A$2:$P$700, MATCH('Auto Menu'!$L94, 'Master List Import'!$M$2:$M$700), 14) -> Baby Powder | N94: =INDEX('Master List Import'!$A$2:$P$700, MATCH('Auto Menu'!$L94, 'Master List Import'!$M$2:$M$700), 16) -> 1.6
B95: 4211 | C95: =INDEX('Master List Import'!$A$2:$P$700, MATCH('Auto Menu'!$B95, 'Master List Import'!$M$2:$M$700), 14) -> Speed Stick, Fresh Scent | D95: =INDEX('Master List Import'!$A$2:$P$700, MATCH('Auto Menu'!$B95, 'Master List Import'!$M$2:$M$700), 16) -> 4.85 | L95: 5440 | M95: =INDEX('Master List Import'!$A$2:$P$700, MATCH('Auto Menu'!$L95, 'Master List Import'!$M$2:$M$700), 14) -> Lip Balm | N95: =INDEX('Master List Import'!$A$2:$P$700, MATCH('Auto Menu'!$L95, 'Master List Import'!$M$2:$M$700), 16) -> 1.5
B96: 4212 | C96: =INDEX('Master List Import'!$A$2:$P$700, MATCH('Auto Menu'!$B96, 'Master List Import'!$M$2:$M$700), 14) -> Degree Solid, Extreme Blast | D96: =INDEX('Master List Import'!$A$2:$P$700, MATCH('Auto Menu'!$B96, 'Master List Import'!$M$2:$M$700), 16) -> 6 | F96: TOOTHPASTE, ORAL HYGIENE | L96: 5500 | M96: =INDEX('Master List Import'!$A$2:$P$700, MATCH('Auto Menu'!$L96, 'Master List Import'!$M$2:$M$700), 14) -> Antifungal Cream | N96: =INDEX('Master List Import'!$A$2:$P$700, MATCH('Auto Menu'!$L96, 'Master List Import'!$M$2:$M$700), 16) -> 4.2
B97: 4213 | C97: =INDEX('Master List Import'!$A$2:$P$700, MATCH('Auto Menu'!$B97, 'Master List Import'!$M$2:$M$700), 14) -> Suave, Powder Scent | D97: =INDEX('Master List Import'!$A$2:$P$700, MATCH('Auto Menu'!$B97, 'Master List Import'!$M$2:$M$700), 16) -> 4.5 | G97: 4400 | H97: =INDEX('Master List Import'!$A$2:$P$700, MATCH('Auto Menu'!$G97, 'Master List Import'!$M$2:$M$700), 14) -> Colgate Regular Toothpaste | I97: =INDEX('Master List Import'!$A$2:$P$700, MATCH('Auto Menu'!$G97, 'Master List Import'!$M$2:$M$700), 16) -> 3.15 | L97: 5510 | M97: =INDEX('Master List Import'!$A$2:$P$700, MATCH('Auto Menu'!$L97, 'Master List Import'!$M$2:$M$700), 14) -> Foot Powder | N97: =INDEX('Master List Import'!$A$2:$P$700, MATCH('Auto Menu'!$L97, 'Master List Import'!$M$2:$M$700), 16) -> 2.85
G98: 4401 | H98: =INDEX('Master List Import'!$A$2:$P$700, MATCH('Auto Menu'!$G98, 'Master List Import'!$M$2:$M$700), 14) -> Close-Up Toothpaste | I98: =INDEX('Master List Import'!$A$2:$P$700, MATCH('Auto Menu'!$G98, 'Master List Import'!$M$2:$M$700), 16) -> 3.95 | L98: 5520 | M98: =INDEX('Master List Import'!$A$2:$P$700, MATCH('Auto Menu'!$L98, 'Master List Import'!$M$2:$M$700), 14) -> Acne Cream | N98: =INDEX('Master List Import'!$A$2:$P$700, MATCH('Auto Menu'!$L98, 'Master List Import'!$M$2:$M$700), 16) -> 3.95
A99: SHAMPOO, CONDITIONER, BODY WASH | G99: 4402 | H99: =INDEX('Master List Import'!$A$2:$P$700, MATCH('Auto Menu'!$G99, 'Master List Import'!$M$2:$M$700), 14) -> Freshmint Toothpaste | I99: =INDEX('Master List Import'!$A$2:$P$700, MATCH('Auto Menu'!$G99, 'Master List Import'!$M$2:$M$700), 16) -> 1 | L99: 5530 | M99: =INDEX('Master List Import'!$A$2:$P$700, MATCH('Auto Menu'!$L99, 'Master List Import'!$M$2:$M$700), 14) -> Hydrocortisone Cream | N99: =INDEX('Master List Import'!$A$2:$P$700, MATCH('Auto Menu'!$L99, 'Master List Import'!$M$2:$M$700), 16) -> 3.05
B100: 5000 | C100: =INDEX('Master List Import'!$A$2:$P$700, MATCH('Auto Menu'!$B100, 'Master List Import'!$M$2:$M$700), 14) -> VO5 Extra Body Shampoo | D100: =INDEX('Master List Import'!$A$2:$P$700, MATCH('Auto Menu'!$B100, 'Master List Import'!$M$2:$M$700), 16) -> 3.5 | G100: 4403 | H100: =INDEX('Master List Import'!$A$2:$P$700, MATCH('Auto Menu'!$G100, 'Master List Import'!$M$2:$M$700), 14) -> Aim Toothpaste | I100: =INDEX('Master List Import'!$A$2:$P$700, MATCH('Auto Menu'!$G100, 'Master List Import'!$M$2:$M$700), 16) -> 4.25 | L100: 5540 | M100: =INDEX('Master List Import'!$A$2:$P$700, MATCH('Auto Menu'!$L100, 'Master List Import'!$M$2:$M$700), 14) -> Medicated Skin Cream | N100: =INDEX('Master List Import'!$A$2:$P$700, MATCH('Auto Menu'!$L100, 'Master List Import'!$M$2:$M$700), 16) -> 2.3
B101: 5001 | C101: =INDEX('Master List Import'!$A$2:$P$700, MATCH('Auto Menu'!$B101, 'Master List Import'!$M$2:$M$700), 14) -> Herbal Shampoo (Vanilla/Vitamin E) | D101: =INDEX('Master List Import'!$A$2:$P$700, MATCH('Auto Menu'!$B101, 'Master List Import'!$M$2:$M$700), 16) -> 3 | G101: 4420 | H101: =INDEX('Master List Import'!$A$2:$P$700, MATCH('Auto Menu'!$G101, 'Master List Import'!$M$2:$M$700), 14) -> Colgate Sensitive Toothpaste | I101: =INDEX('Master List Import'!$A$2:$P$700, MATCH('Auto Menu'!$G101, 'Master List Import'!$M$2:$M$700), 16) -> 12 | L101: 5541 | M101: =INDEX('Master List Import'!$A$2:$P$700, MATCH('Auto Menu'!$L101, 'Master List Import'!$M$2:$M$700), 14) -> Triple Antibiotic Ointment | N101: =INDEX('Master List Import'!$A$2:$P$700, MATCH('Auto Menu'!$L101, 'Master List Import'!$M$2:$M$700), 16) -> 3.5
B102: 5002 | C102: =INDEX('Master List Import'!$A$2:$P$700, MATCH('Auto Menu'!$B102, 'Master List Import'!$M$2:$M$700), 14) -> VO5 Strwb/Crm Shampoo | D102: =INDEX('Master List Import'!$A$2:$P$700, MATCH('Auto Menu'!$B102, 'Master List Import'!$M$2:$M$700), 16) -> 3.5 | G102: 4500 | H102: =INDEX('Master List Import'!$A$2:$P$700, MATCH('Auto Menu'!$G102, 'Master List Import'!$M$2:$M$700), 14) -> Tek Toothbrush | I102: =INDEX('Master List Import'!$A$2:$P$700, MATCH('Auto Menu'!$G102, 'Master List Import'!$M$2:$M$700), 16) -> 1.25 | L102: 5542 | M102: =INDEX('Master List Import'!$A$2:$P$700, MATCH('Auto Menu'!$L102, 'Master List Import'!$M$2:$M$700), 14) -> Hemorrhoid Ointment | N102: =INDEX('Master List Import'!$A$2:$P$700, MATCH('Auto Menu'!$L102, 'Master List Import'!$M$2:$M$700), 16) -> 7.5
B103: 5040 | C103: =INDEX('Master List Import'!$A$2:$P$700, MATCH('Auto Menu'!$B103, 'Master List Import'!$M$2:$M$700), 14) -> Dandruff Shampoo | D103: =INDEX('Master List Import'!$A$2:$P$700, MATCH('Auto Menu'!$B103, 'Master List Import'!$M$2:$M$700), 16) -> 3 | G103: 4501 | H103: =INDEX('Master List Import'!$A$2:$P$700, MATCH('Auto Menu'!$G103, 'Master List Import'!$M$2:$M$700), 14) -> Shorty Toothbrush | I103: =INDEX('Master List Import'!$A$2:$P$700, MATCH('Auto Menu'!$G103, 'Master List Import'!$M$2:$M$700), 16) -> 0.2 | L103: 4800 | M103: =INDEX('Master List Import'!$A$2:$P$700, MATCH('Auto Menu'!$L103, 'Master List Import'!$M$2:$M$700), 14) -> Q-Tips (90ct) | N103: =INDEX('Master List Import'!$A$2:$P$700, MATCH('Auto Menu'!$L103, 'Master List Import'!$M$2:$M$700), 16) -> 2.3
B104: 5041 | C104: =INDEX('Master List Import'!$A$2:$P$700, MATCH('Auto Menu'!$B104, 'Master List Import'!$M$2:$M$700), 14) -> Sulfur 8 Shampoo | D104: =INDEX('Master List Import'!$A$2:$P$700, MATCH('Auto Menu'!$B104, 'Master List Import'!$M$2:$M$700), 16) -> 8.4 | G104: 4502 | H104: =INDEX('Master List Import'!$A$2:$P$700, MATCH('Auto Menu'!$G104, 'Master List Import'!$M$2:$M$700), 14) -> Thumb Toothbrush | I104: =INDEX('Master List Import'!$A$2:$P$700, MATCH('Auto Menu'!$G104, 'Master List Import'!$M$2:$M$700), 16) -> 1 | L104: 4801 | M104: =INDEX('Master List Import'!$A$2:$P$700, MATCH('Auto Menu'!$L104, 'Master List Import'!$M$2:$M$700), 14) -> Handkerchief | N104: =INDEX('Master List Import'!$A$2:$P$700, MATCH('Auto Menu'!$L104, 'Master List Import'!$M$2:$M$700), 16) -> 2.25
B105: 5042 | C105: =INDEX('Master List Import'!$A$2:$P$700, MATCH('Auto Menu'!$B105, 'Master List Import'!$M$2:$M$700), 14) -> Sulfur 8 Medicated Conditioner | D105: =INDEX('Master List Import'!$A$2:$P$700, MATCH('Auto Menu'!$B105, 'Master List Import'!$M$2:$M$700), 16) -> 9 | G105: 4503 | H105: =INDEX('Master List Import'!$A$2:$P$700, MATCH('Auto Menu'!$G105, 'Master List Import'!$M$2:$M$700), 14) -> Colgate Toothbrush, Soft | I105: =INDEX('Master List Import'!$A$2:$P$700, MATCH('Auto Menu'!$G105, 'Master List Import'!$M$2:$M$700), 16) -> 2.6 | L105: 4802 | M105: =INDEX('Master List Import'!$A$2:$P$700, MATCH('Auto Menu'!$L105, 'Master List Import'!$M$2:$M$700), 14) -> Foam Earplugs | N105: =INDEX('Master List Import'!$A$2:$P$700, MATCH('Auto Menu'!$L105, 'Master List Import'!$M$2:$M$700), 16) -> 0.55
B106: 5050 | C106: =INDEX('Master List Import'!$A$2:$P$700, MATCH('Auto Menu'!$B106, 'Master List Import'!$M$2:$M$700), 14) -> VO5 Extra Body Conditioner | D106: =INDEX('Master List Import'!$A$2:$P$700, MATCH('Auto Menu'!$B106, 'Master List Import'!$M$2:$M$700), 16) -> 3.5 | G106: 4520 | H106: =INDEX('Master List Import'!$A$2:$P$700, MATCH('Auto Menu'!$G106, 'Master List Import'!$M$2:$M$700), 14) -> Toothbrush Holder | I106: =INDEX('Master List Import'!$A$2:$P$700, MATCH('Auto Menu'!$G106, 'Master List Import'!$M$2:$M$700), 16) -> 0.55 | L106: 4830 | M106: =INDEX('Master List Import'!$A$2:$P$700, MATCH('Auto Menu'!$L106, 'Master List Import'!$M$2:$M$700), 14) -> Toilet Paper | N106: =INDEX('Master List Import'!$A$2:$P$700, MATCH('Auto Menu'!$L106, 'Master List Import'!$M$2:$M$700), 16) -> 1.3
B107: 5051 | C107: =INDEX('Master List Import'!$A$2:$P$700, MATCH('Auto Menu'!$B107, 'Master List Import'!$M$2:$M$700), 14) -> Herbal Conditioner (Vanilla/Vitamin E) | D107: =INDEX('Master List Import'!$A$2:$P$700, MATCH('Auto Menu'!$B107, 'Master List Import'!$M$2:$M$700), 16) -> 3 | G107: 4530 | H107: =INDEX('Master List Import'!$A$2:$P$700, MATCH('Auto Menu'!$G107, 'Master List Import'!$M$2:$M$700), 14) -> Dental Floss Loops (30ct) | I107: =INDEX('Master List Import'!$A$2:$P$700, MATCH('Auto Menu'!$G107, 'Master List Import'!$M$2:$M$700), 16) -> 7 | L107: 4840 | M107: =INDEX('Master List Import'!$A$2:$P$700, MATCH('Auto Menu'!$L107, 'Master List Import'!$M$2:$M$700), 14) -> Nail Clippers | N107: =INDEX('Master List Import'!$A$2:$P$700, MATCH('Auto Menu'!$L107, 'Master List Import'!$M$2:$M$700), 16) -> 1
B108: 5052 | C108: =INDEX('Master List Import'!$A$2:$P$700, MATCH('Auto Menu'!$B108, 'Master List Import'!$M$2:$M$700), 14) -> VO5 Strwb/Crm Conditioner | D108: =INDEX('Master List Import'!$A$2:$P$700, MATCH('Auto Menu'!$B108, 'Master List Import'!$M$2:$M$700), 16) -> 3.5 | G108: 4600 | H108: =INDEX('Master List Import'!$A$2:$P$700, MATCH('Auto Menu'!$G108, 'Master List Import'!$M$2:$M$700), 14) -> Mouthwash | I108: =INDEX('Master List Import'!$A$2:$P$700, MATCH('Auto Menu'!$G108, 'Master List Import'!$M$2:$M$700), 16) -> 1.5 | L108: 4841 | M108: =INDEX('Master List Import'!$A$2:$P$700, MATCH('Auto Menu'!$L108, 'Master List Import'!$M$2:$M$700), 14) -> Emery Board | N108: =INDEX('Master List Import'!$A$2:$P$700, MATCH('Auto Menu'!$L108, 'Master List Import'!$M$2:$M$700), 16) -> 0.1
B109: 5060 | C109: =INDEX('Master List Import'!$A$2:$P$700, MATCH('Auto Menu'!$B109, 'Master List Import'!$M$2:$M$700), 14) -> Freshscent Shampoo & Bodywash | D109: =INDEX('Master List Import'!$A$2:$P$700, MATCH('Auto Menu'!$B109, 'Master List Import'!$M$2:$M$700), 16) -> 1.5 | G109: 4700 | H109: =INDEX('Master List Import'!$A$2:$P$700, MATCH('Auto Menu'!$G109, 'Master List Import'!$M$2:$M$700), 14) -> Denture Adhesive | I109: =INDEX('Master List Import'!$A$2:$P$700, MATCH('Auto Menu'!$G109, 'Master List Import'!$M$2:$M$700), 16) -> 5.95 | L109: 4842 | M109: =INDEX('Master List Import'!$A$2:$P$700, MATCH('Auto Menu'!$L109, 'Master List Import'!$M$2:$M$700), 14) -> Toe Nail Clippers | N109: =INDEX('Master List Import'!$A$2:$P$700, MATCH('Auto Menu'!$L109, 'Master List Import'!$M$2:$M$700), 16) -> 2.1
B110: 5070 | C110: =INDEX('Master List Import'!$A$2:$P$700, MATCH('Auto Menu'!$B110, 'Master List Import'!$M$2:$M$700), 14) -> White Rain Mens 3-In-1 | D110: =INDEX('Master List Import'!$A$2:$P$700, MATCH('Auto Menu'!$B110, 'Master List Import'!$M$2:$M$700), 16) -> 4 | G110: 4701 | H110: =INDEX('Master List Import'!$A$2:$P$700, MATCH('Auto Menu'!$G110, 'Master List Import'!$M$2:$M$700), 14) -> Freshmint Denture Cleanser Tabs | I110: =INDEX('Master List Import'!$A$2:$P$700, MATCH('Auto Menu'!$G110, 'Master List Import'!$M$2:$M$700), 16) -> 0.25 | L110: 4900 | M110: =INDEX('Master List Import'!$A$2:$P$700, MATCH('Auto Menu'!$L110, 'Master List Import'!$M$2:$M$700), 14) -> Douche | N110: =INDEX('Master List Import'!$A$2:$P$700, MATCH('Auto Menu'!$L110, 'Master List Import'!$M$2:$M$700), 16) -> 3.75
B111: 5082 | C111: =INDEX('Master List Import'!$A$2:$P$700, MATCH('Auto Menu'!$B111, 'Master List Import'!$M$2:$M$700), 14) -> Suave Ocean Breeze Body Wash | D111: =INDEX('Master List Import'!$A$2:$P$700, MATCH('Auto Menu'!$B111, 'Master List Import'!$M$2:$M$700), 16) -> 7.7 | G111: 4710 | H111: =INDEX('Master List Import'!$A$2:$P$700, MATCH('Auto Menu'!$G111, 'Master List Import'!$M$2:$M$700), 14) -> Oral Pain Relief | I111: =INDEX('Master List Import'!$A$2:$P$700, MATCH('Auto Menu'!$G111, 'Master List Import'!$M$2:$M$700), 16) -> 3.5 | L111: 4910 | M111: =INDEX('Master List Import'!$A$2:$P$700, MATCH('Auto Menu'!$L111, 'Master List Import'!$M$2:$M$700), 14) -> Maxipads (14ct) | N111: =INDEX('Master List Import'!$A$2:$P$700, MATCH('Auto Menu'!$L111, 'Master List Import'!$M$2:$M$700), 16) -> 2.65
L112: 4920 | M112: =INDEX('Master List Import'!$A$2:$P$700, MATCH('Auto Menu'!$L112, 'Master List Import'!$M$2:$M$700), 14) -> Tampons (10ct) | N112: =INDEX('Master List Import'!$A$2:$P$700, MATCH('Auto Menu'!$L112, 'Master List Import'!$M$2:$M$700), 16) -> 3.3
A114: MISCELLANEOUS
A115: PLASTICWARE | F115: RELIGIOUS | K115: STATIONERY
B116: 2200 | C116: =INDEX('Master List Import'!$A$2:$P$700, MATCH('Auto Menu'!$B116, 'Master List Import'!$M$2:$M$700), 14) -> Bowl w/Lid (24oz) | D116: =INDEX('Master List Import'!$A$2:$P$700, MATCH('Auto Menu'!$B116, 'Master List Import'!$M$2:$M$700), 16) -> 3.15 | G116: 3600 | H116: * Holy Bible, KJV | I116: =INDEX('Master List Import'!$A$2:$P$700, MATCH('Auto Menu'!$G116, 'Master List Import'!$M$2:$M$700), 16) -> 2.5 | L116: 2650 | M116: =INDEX('Master List Import'!$A$2:$P$700, MATCH('Auto Menu'!$L116, 'Master List Import'!$M$2:$M$700), 14) -> Webster's Dictionary | N116: =INDEX('Master List Import'!$A$2:$P$700, MATCH('Auto Menu'!$L116, 'Master List Import'!$M$2:$M$700), 16) -> 3.5
B117: 2201 | C117: =INDEX('Master List Import'!$A$2:$P$700, MATCH('Auto Menu'!$B117, 'Master List Import'!$M$2:$M$700), 14) -> Tumbler w/Lid (22oz) | D117: =INDEX('Master List Import'!$A$2:$P$700, MATCH('Auto Menu'!$B117, 'Master List Import'!$M$2:$M$700), 16) -> 0.9 | G117: 3601 | H117: * Sagrada Biblia | I117: =INDEX('Master List Import'!$A$2:$P$700, MATCH('Auto Menu'!$G117, 'Master List Import'!$M$2:$M$700), 16) -> 3.5 | L117: 3000 | M117: =INDEX('Master List Import'!$A$2:$P$700, MATCH('Auto Menu'!$L117, 'Master List Import'!$M$2:$M$700), 14) -> Writing Pad (8.5x11, 50pg) | N117: =INDEX('Master List Import'!$A$2:$P$700, MATCH('Auto Menu'!$L117, 'Master List Import'!$M$2:$M$700), 16) -> 2.1
B118: 2202 | C118: =INDEX('Master List Import'!$A$2:$P$700, MATCH('Auto Menu'!$B118, 'Master List Import'!$M$2:$M$700), 14) -> Plastic Mug (12oz) | D118: =INDEX('Master List Import'!$A$2:$P$700, MATCH('Auto Menu'!$B118, 'Master List Import'!$M$2:$M$700), 16) -> 1.5 | G118: 3602 | H118: * NIV Recovery Study Bible | I118: =INDEX('Master List Import'!$A$2:$P$700, MATCH('Auto Menu'!$G118, 'Master List Import'!$M$2:$M$700), 16) -> 13.5 | L118: 3001 | M118: =INDEX('Master List Import'!$A$2:$P$700, MATCH('Auto Menu'!$L118, 'Master List Import'!$M$2:$M$700), 14) -> Writing Pad (8.5x14, 50pg) | N118: =INDEX('Master List Import'!$A$2:$P$700, MATCH('Auto Menu'!$L118, 'Master List Import'!$M$2:$M$700), 16) -> 2.5
...

Sheet Master List Import
A1: Item ID | B1: ItemID | C1: Description | D1: Category | E1: Sales Type | F1: Gender | G1: Last Cost | H1: Vendor ID | I1: Vendor Item | J1: Min Qty | K1: Max Qty | L1: Case Qty | M1: Scan Code | N1: CustomerItemDescription | O1: Multiplier | P1: Stnd Price | Q1: Column17 | R1: Column18 | S1: Column19 | T1: Column20 | U1: Column21 | V1: Column22 | W1: Column23 | X1: Column24 | Y1: Column25 | Z1: Column26
A2: 1001 | B2: 1001 | C2: Thermal Set - Sm | D2: Clothing | E2: Clothing | F2: Both | G2: 4.96 | H2: REI | I2: 1001 | J2: 0 | K2: 0 | L2: 1 | M2: 1001 | N2: Thermal Set (Sm) | O2: 1 | P2: 17.4
A3: 1002 | B3: 1002 | C3: Thermal Set - Md | D3: Clothing | E3: Clothing | F3: Both | G3: 4.96 | H3: REI | I3: 1002 | J3: 0 | K3: 0 | L3: 1 | M3: 1002 | N3: Thermal Set (Md) | O3: 1 | P3: 17.4
A4: 1003 | B4: 1003 | C4: Thermal Set - Lg | D4: Clothing | E4: Clothing | F4: Both | G4: 4.96 | H4: REI | I4: 1003 | J4: 0 | K4: 0 | L4: 1 | M4: 1003 | N4: Thermal Set (Lg) | O4: 1 | P4: 17.4
A5: 1004 | B5: 1004 | C5: Thermal Set - XL | D5: Clothing | E5: Clothing | F5: Both | G5: 4.96 | H5: REI | I5: 1004 | J5: 0 | K5: 0 | L5: 1 | M5: 1004 | N5: Thermal Set (XL) | O5: 1 | P5: 17.4
A6: 1005 | B6: 1005 | C6: Thermal Set - 2X | D6: Clothing | E6: Clothing | F6: Both | G6: 5.84 | H6: REI | I6: 1005 | J6: 0 | K6: 0 | L6: 1 | M6: 1005 | N6: Thermal Set (2X) | O6: 1 | P6: 20.4
A7: 1006 | B7: 1006 | C7: Thermal Set - 3X | D7: Clothing | E7: Clothing | F7: Both | G7: 6.24 | H7: REI | I7: 1006 | J7: 0 | K7: 0 | L7: 1 | M7: 1006 | N7: Thermal Set (3X) | O7: 1 | P7: 21.8
A8: 1007 | B8: 1007 | C8: Thermal Set - 4X | D8: Clothing | E8: Clothing | F8: Both | G8: 6.64 | H8: REI | I8: 1007 | J8: 0 | K8: 0 | L8: 1 | M8: 1007 | N8: Thermal Set (4X) | O8: 1 | P8: 23.2
A9: 1008 | B9: 1008 | C9: Thermal Set - 5X | D9: Clothing | E9: Clothing | F9: Both | G9: 7.2 | H9: REI | I9: 1008 | J9: 0 | K9: 0 | L9: 1 | M9: 1008 | N9: Thermal Set (5X) | O9: 1 | P9: 25.2
A10: 1021 | B10: 1021 | C10: Thermal Top - Sm | D10: Clothing | E10: Clothing | F10: Both | G10: 2.48 | H10: REI | I10: 900701 | J10: 0 | K10: 0 | L10: 1 | M10: 1021 | N10: Thermal Top (Sm) | O10: 1 | P10: 8.7
A11: 1022 | B11: 1022 | C11: Thermal Top - Md | D11: Clothing | E11: Clothing | F11: Both | G11: 2.48 | H11: REI | I11: 900702 | J11: 0 | K11: 0 | L11: 1 | M11: 1022 | N11: Thermal Top (Md) | O11: 1 | P11: 8.7
A12: 1023 | B12: 1023 | C12: Thermal Top - Lg | D12: Clothing | E12: Clothing | F12: Both | G12: 2.48 | H12: REI | I12: 900703 | J12: 0 | K12: 0 | L12: 1 | M12: 1023 | N12: Thermal Top (Lg) | O12: 1 | P12: 8.7
A13: 1024 | B13: 1024 | C13: Thermal Top - XL | D13: Clothing | E13: Clothing | F13: Both | G13: 2.48 | H13: REI | I13: 900704 | J13: 0 | K13: 0 | L13: 1 | M13: 1024 | N13: Thermal Top (XL) | O13: 1 | P13: 8.7
... A519: 8900 | B519: 8900 | C519: Pop's Snack Shack Sugar Free Assorted Fruit Hard Candy | D519: Diabetic | E519: Diabetic | F519: Both | G519: 0.63 | H519: REI | I519: 057626 | J519: 0 | K519: 0 | L519: 1 | M519: 8900 | N519: Sugar Free Assorted Candy | O519: 1 | P519: 2.25
